CodetagCrawler/__init__.py
CodetagCrawler/__main__.py
CodetagCrawler/cli.py
CodetagCrawler/comment_processing.py
CodetagCrawler/csv.py
CodetagCrawler/metadata_handler.py
CodetagCrawler-1.0.17.dist-info/LICENSE
CodetagCrawler-1.0.17.dist-info/METADATA
CodetagCrawler-1.0.17.dist-info/WHEEL
CodetagCrawler-1.0.17.dist-info/top_level.txt
CodetagCrawler-1.0.17.dist-info/RECORD
