Metadata-Version: 2.1
Name: CodetagCrawler
Version: 1.0.17
Summary: This package provides a click interface to a (Python) codetag crawler, which     searches through a target directory for codetags, and formats them to a .csv format     that can be imported to Azure DevOps or other services using equivalent .csv formats.     A config file is provided to define which codetags to search for. Possible codetags are     as of now limited by the .yml format, so codetags like !!! or ??? are not supported as is.
Home-page: https://github.com/jonoddram/CodetagCrawler
Author: Jon Oddvar Rambjør
Author-email: jonoddram@gmail.com
License: UNKNOWN
Platform: UNKNOWN
Classifier: Programming Language :: Python :: 3.7
Classifier: License :: OSI Approved :: MIT License
Classifier: Operating System :: OS Independent
Requires-Python: >=3.7
License-File: LICENSE
Requires-Dist: pyyaml
Requires-Dist: click
